firebase_auth/__init__.py
firebase_auth/admin.py
firebase_auth/apps.py
firebase_auth/authentication.py
firebase_auth/models.py
firebase_auth/settings.py
firebase_auth/views.py
firebase_auth/__pycache__/__init__.cpython-38.pyc
firebase_auth/__pycache__/admin.cpython-38.pyc
firebase_auth/__pycache__/authentication.cpython-38.pyc
firebase_auth/__pycache__/models.cpython-38.pyc
firebase_auth/__pycache__/settings.cpython-38.pyc
firebase_auth/__pycache__/urls.cpython-38.pyc
firebase_auth/__pycache__/views.cpython-38.pyc
firebase_auth/migrations/__init__.py
firebase_auth/migrations/__pycache__/__init__.cpython-38.pyc
django_rest_firebase_auth-0.2.0.dist-info/LICENSE
django_rest_firebase_auth-0.2.0.dist-info/METADATA
django_rest_firebase_auth-0.2.0.dist-info/WHEEL
django_rest_firebase_auth-0.2.0.dist-info/top_level.txt
django_rest_firebase_auth-0.2.0.dist-info/RECORD
